meadowrun/__init__.py
meadowrun/_vendor/__init__.py
meadowrun/_vendor/aiodocker/__init__.py
meadowrun/_vendor/aiodocker/channel.py
meadowrun/_vendor/aiodocker/configs.py
meadowrun/_vendor/aiodocker/constants.py
meadowrun/_vendor/aiodocker/containers.py
meadowrun/_vendor/aiodocker/docker.py
meadowrun/_vendor/aiodocker/events.py
meadowrun/_vendor/aiodocker/exceptions.py
meadowrun/_vendor/aiodocker/execs.py
meadowrun/_vendor/aiodocker/images.py
meadowrun/_vendor/aiodocker/jsonstream.py
meadowrun/_vendor/aiodocker/logs.py
meadowrun/_vendor/aiodocker/multiplexed.py
meadowrun/_vendor/aiodocker/networks.py
meadowrun/_vendor/aiodocker/nodes.py
meadowrun/_vendor/aiodocker/py.typed
meadowrun/_vendor/aiodocker/secrets.py
meadowrun/_vendor/aiodocker/services.py
meadowrun/_vendor/aiodocker/stream.py
meadowrun/_vendor/aiodocker/swarm.py
meadowrun/_vendor/aiodocker/system.py
meadowrun/_vendor/aiodocker/tasks.py
meadowrun/_vendor/aiodocker/utils.py
meadowrun/_vendor/aiodocker/volumes.py
meadowrun/_vendor/fastcdc/__init__.py
meadowrun/_vendor/fastcdc/fastcdc_py.py
meadowrun/_vendor/gcloud/__init__.py
meadowrun/_vendor/gcloud/aio/__init__.py
meadowrun/_vendor/gcloud/aio/auth/__init__.py
meadowrun/_vendor/gcloud/aio/auth/build_constants.py
meadowrun/_vendor/gcloud/aio/auth/iam.py
meadowrun/_vendor/gcloud/aio/auth/py.typed
meadowrun/_vendor/gcloud/aio/auth/session.py
meadowrun/_vendor/gcloud/aio/auth/token.py
meadowrun/_vendor/gcloud/aio/auth/utils.py
meadowrun/_vendor/gcloud/aio/storage/__init__.py
meadowrun/_vendor/gcloud/aio/storage/blob.py
meadowrun/_vendor/gcloud/aio/storage/bucket.py
meadowrun/_vendor/gcloud/aio/storage/constants.py
meadowrun/_vendor/gcloud/aio/storage/py.typed
meadowrun/_vendor/gcloud/aio/storage/storage.py
meadowrun/_vendor/platformdirs/__init__.py
meadowrun/_vendor/platformdirs/android.py
meadowrun/_vendor/platformdirs/api.py
meadowrun/_vendor/platformdirs/macos.py
meadowrun/_vendor/platformdirs/py.typed
meadowrun/_vendor/platformdirs/unix.py
meadowrun-0.2.16.dist-info/entry_points.txt
meadowrun-0.2.16.dist-info/LICENSE
meadowrun-0.2.16.dist-info/WHEEL
meadowrun-0.2.16.dist-info/METADATA
meadowrun-0.2.16.dist-info/RECORD
